Metadata-Version: 2.1
Name: Pyl3s
Version: 0.0.1
Summary: Ainda em desenvolvimento
Author: Pedro Vitor, Marcos Andre
Author-email: pedro.passos@ufpi.edu.br
License: MIT License
Keywords: files
License-File: LICENSE
